ullme/__init__.py
ullme/args.py
ullme/special_tokens.py
ullme/train.py
ullme/data_modules/__init__.py
ullme/data_modules/rep_learning_datamodule.py
ullme/data_modules/rep_learning_dataset.py
ullme/eval/__init__.py
ullme/eval/constants.py
ullme/eval/eval.py
ullme/models/__init__.py
ullme/models/modeling_bidirectional_cohere.py
ullme/models/modeling_bidirectional_gemma.py
ullme/models/modeling_bidirectional_gemma2.py
ullme/models/modeling_bidirectional_llama.py
ullme/models/modeling_bidirectional_mistral.py
ullme/models/modeling_bidirectional_phi.py
ullme/models/modeling_bidirectional_phi3.py
ullme/models/modeling_bidirectional_qwen2.py
ullme/models/ullme.py
ullme/models/utils.py
ullme/trainer/__init__.py
ullme/trainer/gradcache_trainer.py
ullme/trainer/loss.py
ullme/trainer/utils.py
ullme-0.0.3.dist-info/LICENSE
ullme-0.0.3.dist-info/METADATA
ullme-0.0.3.dist-info/WHEEL
ullme-0.0.3.dist-info/top_level.txt
ullme-0.0.3.dist-info/RECORD
