Metadata-Version: 2.1
Name: ullme
Version: 0.0.3
Summary: ULLME: A Unified Framework for Large Language Model Embeddings with Generation-Augmented Learning
Home-page: https://github.com/nlp-uoregon/ullme
Author: NLP Group at the University of Oregon
Author-email: hieum@uoregon.edu
License: Apache License 2.0
Classifier: Development Status :: 4 - Beta
Classifier: Intended Audience :: Developers
Classifier: Intended Audience :: Education
Classifier: Intended Audience :: Science/Research
Classifier: Intended Audience :: Information Technology
Classifier: Topic :: Scientific/Engineering
Classifier: Topic :: Scientific/Engineering :: Artificial Intelligence
Classifier: Topic :: Scientific/Engineering :: Information Analysis
Classifier: Topic :: Text Processing
Classifier: Topic :: Text Processing :: Linguistic
Classifier: Topic :: Software Development
Classifier: Topic :: Software Development :: Libraries
Classifier: Programming Language :: Python :: 3.6
Classifier: Programming Language :: Python :: 3.7
Classifier: Programming Language :: Python :: 3.8
Classifier: Programming Language :: Python :: 3.9
Classifier: Programming Language :: Python :: 3.10
License-File: LICENSE
Requires-Dist: numpy
Requires-Dist: brotli
Requires-Dist: torch
Requires-Dist: cffi
Requires-Dist: einops
Requires-Dist: faiss-cpu
Requires-Dist: gmpy2
Requires-Dist: ipykernel
Requires-Dist: lightning
Requires-Dist: mkl-fft
Requires-Dist: mkl-random
Requires-Dist: mteb
Requires-Dist: peft
Requires-Dist: pip-chill
Requires-Dist: pysocks
Requires-Dist: pytorch-metric-learning
Requires-Dist: ruamel.yaml
Requires-Dist: wandb
